setup.py
bae_log/__init__.py
bae_log/handlers.py
bae_log.egg-info/PKG-INFO
bae_log.egg-info/SOURCES.txt
bae_log.egg-info/dependency_links.txt
bae_log.egg-info/not-zip-safe
bae_log.egg-info/requires.txt
bae_log.egg-info/top_level.txt
bae_log/lib/__init__.py
bae_log/lib/client.py
bae_log/lib/constants.py
bae_log/lib/utils.py
bae_log/lib/logchain/__init__.py
bae_log/lib/logchain/constants.py
bae_log/lib/logchain/logchain.py
bae_log/lib/logchain/ttypes.py