Metadata-Version: 1.1
Name: bae-log
Version: 1.0.0
Summary: BAE Log SDK for V3.0
Home-page: http://developer.baidu.com
Author: Zhang Guanxing
Author-email: zhangguanxing01@baidu.com
License: UNKNOWN
Keywords: bae log sdk
Platform: UNKNOWN
Classifier: Development Status :: 4 - Beta
Classifier: Topic :: Utilities
Classifier: Programming Language :: Python :: 2 :: Only
